<?xml version="1.0" encoding="UTF-8"?>
<con:soapui-project id="f8d6e818-f536-42b3-a5e1-5738d797ac36" activeEnvironment="Default" name="bulbiz?_wadl" soapui-version="5.2.1" xmlns:con="http://eviware.com/soapui/config"><con:settings><con:setting id="com.eviware.soapui.impl.wsdl.actions.iface.tools.soapui.TestRunnerAction@values-local"><![CDATA[<xml-fragment xmlns:con="http://eviware.com/soapui/config">
  <con:entry key="Environment" value="Default"/>
  <con:entry key="Global Properties" value=""/>
  <con:entry key="TestSuite" value="Bulbiz Test"/>
  <con:entry key="Password" value=""/>
  <con:entry key="TestRunner Path" value=""/>
  <con:entry key="Tool Args" value=""/>
  <con:entry key="Ignore Errors" value="false"/>
  <con:entry key="Host:Port" value=""/>
  <con:entry key="user-settings.xml Password" value=""/>
  <con:entry key="WSS Password Type" value=""/>
  <con:entry key="Save Project" value="false"/>
  <con:entry key="Enable UI" value="false"/>
  <con:entry key="System Properties" value=""/>
  <con:entry key="Domain" value=""/>
  <con:entry key="Coverage Report" value="false"/>
  <con:entry key="Export JUnit Results" value="false"/>
  <con:entry key="Export JUnit Results with test properties" value="false"/>
  <con:entry key="Open Report" value="false"/>
  <con:entry key="Project Properties" value=""/>
  <con:entry key="Export All" value="false"/>
  <con:entry key="Project Password" value=""/>
  <con:entry key="Report Format(s)" value=""/>
  <con:entry key="TestCase" value="&lt;all>"/>
  <con:entry key="Print Report" value="false"/>
  <con:entry key="Username" value=""/>
  <con:entry key="Root Folder" value=""/>
  <con:entry key="Select Report Type" value=""/>
  <con:entry key="Save After" value="false"/>
  <con:entry key="Add Settings" value="false"/>
  <con:entry key="Endpoint" value=""/>
</xml-fragment>]]></con:setting></con:settings><con:interface xsi:type="con:RestService" id="1a278799-156f-41dc-9d5e-bfbbd1052719" wadlVersion="http://wadl.dev.java.net/2009/02" name="bulbiz?_wadl" type="rest" basePath="/cxf/bulbiz" definitionUrl="http://localhost:8181/cxf/bulbiz?_wadl" xmlns:xsi="http://www.w3.org/2001/XMLSchema-instance"><con:settings/><con:definitionCache type="TEXT" rootPart="http://localhost:8181/cxf/bulbiz?_wadl"><con:part><con:url>http://localhost:8181/cxf/bulbiz?_wadl</con:url><con:content><![CDATA[<application xmlns="http://wadl.dev.java.net/2009/02" xmlns:xs="http://www.w3.org/2001/XMLSchema">
  <grammars/>
  <resources base="http://localhost:8181/cxf/bulbiz">
    <resource path="/client">
      <method name="POST">
        <request>
          <param name="name" style="query" type="xs:string"/>
        </request>
        <response>
          <representation mediaType="application/json"/>
        </response>
      </method>
      <resource path="/{clientId}/orders">
        <param name="clientId" style="template" type="xs:string"/>
        <method name="GET">
          <request/>
          <response>
            <representation mediaType="application/json"/>
          </response>
        </method>
      </resource>
      <resource path="/{id}">
        <param name="id" style="template" type="xs:string"/>
        <method name="DELETE">
          <request/>
          <response>
            <representation mediaType="application/json"/>
          </response>
        </method>
        <method name="GET">
          <request/>
          <response>
            <representation mediaType="application/json"/>
          </response>
        </method>
        <method name="PUT">
          <request>
            <param name="name" style="query" type="xs:string"/>
          </request>
          <response>
            <representation mediaType="application/json"/>
          </response>
        </method>
      </resource>
    </resource>
    <resource path="/cart">
      <resource path="/client/{id}/">
        <param name="id" style="template" type="xs:string"/>
        <method name="DELETE">
          <request/>
          <response>
            <representation mediaType="application/json"/>
          </response>
        </method>
        <method name="GET">
          <request/>
          <response>
            <representation mediaType="application/json"/>
          </response>
        </method>
        <method name="POST">
          <request>
            <param name="form" style="query" type="xs:string"/>
            <param name="color" style="query" type="xs:string"/>
            <param name="quantity" style="query" type="xs:string"/>
          </request>
          <response>
            <representation mediaType="application/json"/>
          </response>
        </method>
      </resource>
      <resource path="/{orderId}/client/{clientId}/">
        <param name="orderId" style="template" type="xs:string"/>
        <param name="clientId" style="template" type="xs:string"/>
        <method name="GET">
          <request/>
          <response>
            <representation mediaType="application/json"/>
          </response>
        </method>
      </resource>
    </resource>
    <resource path="/delivery">
      <resource path="/destination/client/{clientId}">
        <param name="clientId" style="template" type="xs:string"/>
        <method name="POST">
          <request>
            <param name="address" style="query" type="xs:string"/>
          </request>
          <response>
            <representation mediaType="application/json"/>
          </response>
        </method>
      </resource>
      <resource path="/manufacturing/order/{orderId}/client/{clientId}">
        <param name="orderId" style="template" type="xs:string"/>
        <param name="clientId" style="template" type="xs:string"/>
        <method name="GET">
          <request/>
          <response>
            <representation mediaType="application/json"/>
          </response>
        </method>
      </resource>
      <resource path="/state/order/{orderId}/client/{clientId}">
        <param name="orderId" style="template" type="xs:string"/>
        <param name="clientId" style="template" type="xs:string"/>
        <method name="GET">
          <request/>
          <response>
            <representation mediaType="application/json"/>
          </response>
        </method>
      </resource>
    </resource>
    <resource path="/display">
      <resource path="/bulbs">
        <method name="GET">
          <response>
            <representation mediaType="application/json"/>
          </response>
        </method>
      </resource>
      <resource path="/order/{userId}/{orderId}">
        <param name="userId" style="template" type="xs:string"/>
        <param name="orderId" style="template" type="xs:string"/>
        <method name="GET">
          <request/>
          <response>
            <representation mediaType="application/json"/>
          </response>
        </method>
      </resource>
      <resource path="/orders">
        <method name="GET">
          <response>
            <representation mediaType="application/json"/>
          </response>
        </method>
      </resource>
      <resource path="/users">
        <method name="GET">
          <response>
            <representation mediaType="application/json"/>
          </response>
        </method>
      </resource>
    </resource>
    <resource path="/stock">
      <method name="GET">
        <response>
          <representation mediaType="application/json"/>
        </response>
      </method>
      <method name="POST">
        <request>
          <param name="form" style="query" type="xs:string"/>
          <param name="color" style="query" type="xs:string"/>
          <param name="quantity" style="query" type="xs:string"/>
        </request>
        <response>
          <representation mediaType="application/json"/>
        </response>
      </method>
    </resource>
    <resource path="/transaction">
      <resource path="/pay/client/{userId}/order/{orderId}">
        <param name="userId" style="template" type="xs:string"/>
        <param name="orderId" style="template" type="xs:string"/>
        <method name="POST">
          <request>
            <param name="numero" style="query" type="xs:string"/>
            <param name="date" style="query" type="xs:string"/>
            <param name="sc" style="query" type="xs:string"/>
          </request>
          <response>
            <representation mediaType="application/json"/>
          </response>
        </method>
      </resource>
      <resource path="/price/client/{userId}">
        <param name="userId" style="template" type="xs:string"/>
        <method name="GET">
          <request/>
          <response>
            <representation mediaType="application/json"/>
          </response>
        </method>
      </resource>
    </resource>
  </resources>
</application>]]></con:content><con:type>http://wadl.dev.java.net/2009/02</con:type></con:part></con:definitionCache><con:endpoints><con:endpoint>http://localhost:8181</con:endpoint></con:endpoints><con:resource name="/client" path="/client" id="7318c708-c8b4-46a1-a284-41b242eb3acc"><con:settings/><con:parameters/><con:resource name="/{clientId}/orders" path="/{clientId}/orders" id="af4b9f99-0611-4f75-93ed-703466c3b5eb"><con:settings/><con:parameters><con:parameter><con:name>clientId</con:name><con:value xsi:nil="true"/><con:style>TEMPLATE</con:style><con:default xsi:nil="true"/></con:parameter></con:parameters><con:method name="GET" id="927f5e3d-b55f-487a-8aa8-0ee33bd322de" method="GET"><con:settings/><con:parameters/><con:representation type="RESPONSE" id=""><con:mediaType>application/json</con:mediaType><con:params/><con:element xsi:nil="true"/><con:description xsi:nil="true"/></con:representation><con:request name="Request 1" id="d8884899-2368-4de3-a0b7-cfb4a49bae46" mediaType="application/json"><con:settings/><con:endpoint>http://localhost:8181</con:endpoint><con:parameters/></con:request></con:method></con:resource><con:resource name="/{id}" path="/{id}" id="67d1b804-bc2f-4648-a040-e6391e130f04"><con:settings/><con:parameters><con:parameter><con:name>id</con:name><con:value xsi:nil="true"/><con:style>TEMPLATE</con:style><con:default xsi:nil="true"/></con:parameter></con:parameters><con:method name="DELETE" id="1312540e-404b-48b3-ba93-414f48ae1818" method="DELETE"><con:settings/><con:parameters/><con:representation type="RESPONSE" id=""><con:mediaType>application/json</con:mediaType><con:params/><con:element xsi:nil="true"/><con:description xsi:nil="true"/></con:representation><con:request name="Request 1" id="0d771f40-e100-4be8-b0d9-01c2392349ad" mediaType="application/json"><con:settings/><con:endpoint>http://localhost:8181</con:endpoint><con:parameters/></con:request></con:method><con:method name="GET" id="d370b997-07e4-43a9-86c8-c10218637dfc" method="GET"><con:settings/><con:parameters/><con:representation type="RESPONSE" id=""><con:mediaType>application/json</con:mediaType><con:params/><con:element xsi:nil="true"/><con:description xsi:nil="true"/></con:representation><con:request name="Request 1" id="f32e35bf-7dc5-45cc-aeae-2c4bedafc3af" mediaType="application/json"><con:settings/><con:endpoint>http://localhost:8181</con:endpoint><con:parameters/></con:request></con:method><con:method name="PUT" id="1f314710-f617-43f7-8f26-c17ec42a6d7c" method="PUT"><con:settings/><con:parameters><con:parameter><con:name>name</con:name><con:value xsi:nil="true"/><con:style>QUERY</con:style><con:default xsi:nil="true"/></con:parameter></con:parameters><con:representation type="RESPONSE" id=""><con:mediaType>application/json</con:mediaType><con:params/><con:element xsi:nil="true"/><con:description xsi:nil="true"/></con:representation><con:request name="Request 1" id="81b4f749-2230-4c2b-9015-91d8ee53a036" mediaType="application/json"><con:settings/><con:endpoint>http://localhost:8181</con:endpoint><con:parameters/></con:request></con:method></con:resource><con:method name="POST" id="1f7ad62b-8b25-4be8-9fa5-74fc859364eb" method="POST"><con:settings/><con:parameters><con:parameter><con:name>name</con:name><con:value xsi:nil="true"/><con:style>QUERY</con:style><con:default xsi:nil="true"/></con:parameter></con:parameters><con:representation type="RESPONSE" id=""><con:mediaType>application/json</con:mediaType><con:params/><con:element xsi:nil="true"/><con:description xsi:nil="true"/></con:representation><con:request name="Request 1" id="74804e59-3896-4567-8833-220c9f3193e2" mediaType="application/json" postQueryString="false"><con:settings/><con:endpoint>http://localhost:8181</con:endpoint><con:request/><con:credentials><con:authType>No Authorization</con:authType></con:credentials><con:jmsConfig JMSDeliveryMode="PERSISTENT"/><con:jmsPropertyConfig/><con:parameters/></con:request></con:method></con:resource><con:resource name="/cart" path="/cart" id="d458083d-f0e8-484c-a7dd-0cdd161d8ae1"><con:settings/><con:parameters/><con:resource name="/client/{id}/" path="/client/{id}/" id="024e0672-a400-4e27-8e56-6c8ae1b53c13"><con:settings/><con:parameters><con:parameter><con:name>id</con:name><con:value xsi:nil="true"/><con:style>TEMPLATE</con:style><con:default xsi:nil="true"/></con:parameter></con:parameters><con:method name="DELETE" id="53a04d5a-f2ef-417b-9ee1-c290c6c1e979" method="DELETE"><con:settings/><con:parameters/><con:representation type="RESPONSE" id=""><con:mediaType>application/json</con:mediaType><con:params/><con:element xsi:nil="true"/><con:description xsi:nil="true"/></con:representation><con:request name="Request 1" id="d4b3b4b9-f4d8-45db-bf10-4fd838d1dca5" mediaType="application/json"><con:settings/><con:endpoint>http://localhost:8181</con:endpoint><con:parameters/></con:request></con:method><con:method name="GET" id="8dcdd004-738c-43f1-b8b6-0f4695ef6536" method="GET"><con:settings/><con:parameters/><con:representation type="RESPONSE" id=""><con:mediaType>application/json</con:mediaType><con:params/><con:element xsi:nil="true"/><con:description xsi:nil="true"/></con:representation><con:request name="Request 1" id="a5eb6633-bc8d-4690-a152-0e0a7e8e3b60" mediaType="application/json"><con:settings/><con:endpoint>http://localhost:8181</con:endpoint><con:parameters/></con:request></con:method><con:method name="POST" id="25f33375-90c5-45b2-b0f2-a85df9be3ef3" method="POST"><con:settings/><con:parameters><con:parameter><con:name>form</con:name><con:value>oval</con:value><con:style>QUERY</con:style><con:default>oval</con:default></con:parameter><con:parameter><con:name>color</con:name><con:value>blue</con:value><con:style>QUERY</con:style><con:default>blue</con:default></con:parameter><con:parameter><con:name>quantity</con:name><con:value xsi:nil="true"/><con:style>QUERY</con:style><con:default xsi:nil="true"/></con:parameter></con:parameters><con:representation type="RESPONSE" id=""><con:mediaType>application/json</con:mediaType><con:params/><con:element xsi:nil="true"/><con:description xsi:nil="true"/></con:representation><con:request name="Request 1" id="9a0b1c33-4c14-42ae-adbe-0a6df43c8cff" mediaType="application/json"><con:settings/><con:endpoint>http://localhost:8181</con:endpoint><con:parameters/></con:request></con:method></con:resource><con:resource name="/{orderId}/client/{clientId}/" path="/{orderId}/client/{clientId}/" id="897e13b4-7920-44bb-ad00-42c1c89ff405"><con:settings/><con:parameters><con:parameter><con:name>orderId</con:name><con:value xsi:nil="true"/><con:style>TEMPLATE</con:style><con:default xsi:nil="true"/></con:parameter><con:parameter><con:name>clientId</con:name><con:value xsi:nil="true"/><con:style>TEMPLATE</con:style><con:default xsi:nil="true"/></con:parameter></con:parameters><con:method name="GET" id="7c291b2a-a65c-4311-b577-9143cb690a12" method="GET"><con:settings/><con:parameters/><con:representation type="RESPONSE" id=""><con:mediaType>application/json</con:mediaType><con:params/><con:element xsi:nil="true"/><con:description xsi:nil="true"/></con:representation><con:request name="Request 1" id="25cdf8d2-1661-4114-827e-b942d94234cd" mediaType="application/json"><con:settings/><con:endpoint>http://localhost:8181</con:endpoint><con:parameters/></con:request></con:method></con:resource></con:resource><con:resource name="/delivery" path="/delivery" id="cb29b941-a728-4b7b-9c3c-5e010eca4b32"><con:settings/><con:parameters/><con:resource name="/destination/client/{clientId}" path="/destination/client/{clientId}" id="4c964593-a7ea-4fa8-bf5a-d9f48560e9b3"><con:settings/><con:parameters><con:parameter><con:name>clientId</con:name><con:value xsi:nil="true"/><con:style>TEMPLATE</con:style><con:default xsi:nil="true"/></con:parameter></con:parameters><con:method name="POST" id="5365eeee-03c4-4b5b-a362-f716e4c4a0ca" method="POST"><con:settings/><con:parameters><con:parameter><con:name>address</con:name><con:value xsi:nil="true"/><con:style>QUERY</con:style><con:default xsi:nil="true"/></con:parameter></con:parameters><con:representation type="RESPONSE" id=""><con:mediaType>application/json</con:mediaType><con:params/><con:element xsi:nil="true"/><con:description xsi:nil="true"/></con:representation><con:request name="Request 1" id="43c54da4-fcbc-43bd-90ba-fb363cb8c75f" mediaType="application/json"><con:settings/><con:endpoint>http://localhost:8181</con:endpoint><con:parameters/></con:request></con:method></con:resource><con:resource name="/manufacturing/order/{orderId}/client/{clientId}" path="/manufacturing/order/{orderId}/client/{clientId}" id="342c8040-e676-495a-81f0-80b22a3cfc43"><con:settings/><con:parameters><con:parameter><con:name>orderId</con:name><con:value xsi:nil="true"/><con:style>TEMPLATE</con:style><con:default xsi:nil="true"/></con:parameter><con:parameter><con:name>clientId</con:name><con:value xsi:nil="true"/><con:style>TEMPLATE</con:style><con:default xsi:nil="true"/></con:parameter></con:parameters><con:method name="GET" id="8ea68ba3-b7cc-4e38-bcc7-e113b22d28fd" method="GET"><con:settings/><con:parameters/><con:representation type="RESPONSE" id=""><con:mediaType>application/json</con:mediaType><con:params/><con:element xsi:nil="true"/><con:description xsi:nil="true"/></con:representation><con:request name="Request 1" id="dfb74fd9-3660-4678-99d4-049a0141dff7" mediaType="application/json"><con:settings/><con:endpoint>http://localhost:8181</con:endpoint><con:parameters/></con:request></con:method></con:resource><con:resource name="/state/order/{orderId}/client/{clientId}" path="/state/order/{orderId}/client/{clientId}" id="e5055d13-5bd2-4687-8a74-0b993d5a458b"><con:settings/><con:parameters><con:parameter><con:name>orderId</con:name><con:value xsi:nil="true"/><con:style>TEMPLATE</con:style><con:default xsi:nil="true"/></con:parameter><con:parameter><con:name>clientId</con:name><con:value xsi:nil="true"/><con:style>TEMPLATE</con:style><con:default xsi:nil="true"/></con:parameter></con:parameters><con:method name="GET" id="544194b7-a54b-4843-8e9b-c303da591004" method="GET"><con:settings/><con:parameters/><con:representation type="RESPONSE" id=""><con:mediaType>application/json</con:mediaType><con:params/><con:element xsi:nil="true"/><con:description xsi:nil="true"/></con:representation><con:request name="Request 1" id="f8a6d246-383e-4a97-8cc3-c663ef2dd0dd" mediaType="application/json"><con:settings/><con:endpoint>http://localhost:8181</con:endpoint><con:parameters/></con:request></con:method></con:resource></con:resource><con:resource name="/display" path="/display" id="5d77a7aa-7b3b-45a7-9ea9-ffc1c1028d5b"><con:settings/><con:parameters/><con:resource name="/bulbs" path="/bulbs" id="9bf53c2f-b677-412b-a280-ac6fe8bf65e9"><con:settings/><con:parameters/><con:method name="GET" id="1877668f-0a7a-49c7-8987-a46aae7cab03" method="GET"><con:settings/><con:parameters/><con:representation type="RESPONSE" id=""><con:mediaType>application/json</con:mediaType><con:params/><con:element xsi:nil="true"/><con:description xsi:nil="true"/></con:representation><con:request name="Request 1" id="7953a20c-ed91-4b32-809b-d2f162802922" mediaType="application/json"><con:settings/><con:endpoint>http://localhost:8181</con:endpoint><con:parameters/></con:request></con:method></con:resource><con:resource name="/order/{userId}/{orderId}" path="/order/{userId}/{orderId}" id="3ab01a76-e8a8-4b60-b48f-941fc049a841"><con:settings/><con:parameters><con:parameter><con:name>userId</con:name><con:value xsi:nil="true"/><con:style>TEMPLATE</con:style><con:default xsi:nil="true"/></con:parameter><con:parameter><con:name>orderId</con:name><con:value xsi:nil="true"/><con:style>TEMPLATE</con:style><con:default xsi:nil="true"/></con:parameter></con:parameters><con:method name="GET" id="91d862d3-05f2-47ce-813b-59ea5a7fb9a1" method="GET"><con:settings/><con:parameters/><con:representation type="RESPONSE" id=""><con:mediaType>application/json</con:mediaType><con:params/><con:element xsi:nil="true"/><con:description xsi:nil="true"/></con:representation><con:request name="Request 1" id="a91b498c-3373-4f30-89e3-bd17c5fda98b" mediaType="application/json"><con:settings/><con:endpoint>http://localhost:8181</con:endpoint><con:parameters/></con:request></con:method></con:resource><con:resource name="/orders" path="/orders" id="c6f6ff26-8fae-4b69-b7ac-d03511948c1d"><con:settings/><con:parameters/><con:method name="GET" id="0c4be664-37e1-4832-a8a7-bc3b99043b50" method="GET"><con:settings/><con:parameters/><con:representation type="RESPONSE" id=""><con:mediaType>application/json</con:mediaType><con:params/><con:element xsi:nil="true"/><con:description xsi:nil="true"/></con:representation><con:request name="Request 1" id="2f05c0fd-4e84-4505-bc4e-bd469146ff06" mediaType="application/json"><con:settings/><con:endpoint>http://localhost:8181</con:endpoint><con:parameters/></con:request></con:method></con:resource><con:resource name="/users" path="/users" id="4ef1be0b-0ff1-4d8a-b86e-59cf1362a56b"><con:settings/><con:parameters/><con:method name="GET" id="c0abf604-1e75-463f-92b5-ad99c28016a2" method="GET"><con:settings/><con:parameters/><con:representation type="RESPONSE" id=""><con:mediaType>application/json</con:mediaType><con:params/><con:element xsi:nil="true"/><con:description xsi:nil="true"/></con:representation><con:request name="Request 1" id="7408cf1b-86cb-48ad-8588-f1a60a8bddd9" mediaType="application/json"><con:settings/><con:endpoint>http://localhost:8181</con:endpoint><con:parameters/></con:request></con:method></con:resource></con:resource><con:resource name="/stock" path="/stock" id="0a2eb62f-6b0a-4c1a-ab77-74e380e215a9"><con:settings/><con:parameters/><con:method name="GET" id="ea8191ee-1bbe-4e8b-bbd7-8dffdefeafe7" method="GET"><con:settings/><con:parameters/><con:representation type="RESPONSE" id=""><con:mediaType>application/json</con:mediaType><con:params/><con:element xsi:nil="true"/><con:description xsi:nil="true"/></con:representation><con:request name="Request 1" id="855f7048-e038-4c5d-82ce-219b8b38ad2a" mediaType="application/json"><con:settings/><con:endpoint>http://localhost:8181</con:endpoint><con:parameters/></con:request></con:method><con:method name="POST" id="ba3adba4-426a-455f-8ed1-0d0940a37cbe" method="POST"><con:settings/><con:parameters><con:parameter><con:name>form</con:name><con:value xsi:nil="true"/><con:style>QUERY</con:style><con:default xsi:nil="true"/></con:parameter><con:parameter><con:name>color</con:name><con:value xsi:nil="true"/><con:style>QUERY</con:style><con:default xsi:nil="true"/></con:parameter><con:parameter><con:name>quantity</con:name><con:value xsi:nil="true"/><con:style>QUERY</con:style><con:default xsi:nil="true"/></con:parameter></con:parameters><con:representation type="RESPONSE" id=""><con:mediaType>application/json</con:mediaType><con:params/><con:element xsi:nil="true"/><con:description xsi:nil="true"/></con:representation><con:request name="Request 1" id="f72b2842-3dbc-4fe4-b050-8f99de6635f1" mediaType="application/json" postQueryString="false"><con:settings/><con:endpoint>http://localhost:8181</con:endpoint><con:request/><con:credentials><con:authType>No Authorization</con:authType></con:credentials><con:jmsConfig JMSDeliveryMode="PERSISTENT"/><con:jmsPropertyConfig/><con:parameters/></con:request></con:method></con:resource><con:resource name="/transaction" path="/transaction" id="69b6cd69-0d4c-494a-acec-9b86fc027969"><con:settings/><con:parameters/><con:resource name="/pay/client/{userId}/order/{orderId}" path="/pay/client/{userId}/order/{orderId}" id="03069e84-d8c3-4223-ba4b-01f688466e22"><con:settings/><con:parameters><con:parameter><con:name>userId</con:name><con:value xsi:nil="true"/><con:style>TEMPLATE</con:style><con:default xsi:nil="true"/></con:parameter><con:parameter><con:name>orderId</con:name><con:value xsi:nil="true"/><con:style>TEMPLATE</con:style><con:default xsi:nil="true"/></con:parameter></con:parameters><con:method name="POST" id="efd1f890-287c-485d-a8ab-dad497c259bc" method="POST"><con:settings/><con:parameters><con:parameter><con:name>numero</con:name><con:value xsi:nil="true"/><con:style>QUERY</con:style><con:default xsi:nil="true"/></con:parameter><con:parameter><con:name>date</con:name><con:value xsi:nil="true"/><con:style>QUERY</con:style><con:default xsi:nil="true"/></con:parameter><con:parameter><con:name>sc</con:name><con:value xsi:nil="true"/><con:style>QUERY</con:style><con:default xsi:nil="true"/></con:parameter></con:parameters><con:representation type="RESPONSE" id=""><con:mediaType>application/json</con:mediaType><con:params/><con:element xsi:nil="true"/><con:description xsi:nil="true"/></con:representation><con:request name="Request 1" id="c1086913-e438-4d31-bdb1-a3f3cbb71567" mediaType="application/json"><con:settings/><con:endpoint>http://localhost:8181</con:endpoint><con:parameters/></con:request></con:method></con:resource><con:resource name="/price/client/{userId}" path="/price/client/{userId}" id="bd1d69ac-4fbb-45e7-a5c5-9bbbb2b49504"><con:settings/><con:parameters><con:parameter><con:name>userId</con:name><con:value xsi:nil="true"/><con:style>TEMPLATE</con:style><con:default xsi:nil="true"/></con:parameter></con:parameters><con:method name="GET" id="29d32c97-bcf0-422e-879e-b600c1e991e1" method="GET"><con:settings/><con:parameters/><con:representation type="RESPONSE" id=""><con:mediaType>application/json</con:mediaType><con:params/><con:element xsi:nil="true"/><con:description xsi:nil="true"/></con:representation><con:request name="Request 1" id="7abda849-c99f-488e-9992-074239bb8edc" mediaType="application/json"><con:settings/><con:endpoint>http://localhost:8181</con:endpoint><con:parameters/></con:request></con:method></con:resource></con:resource></con:interface><con:testSuite id="01d806ac-3d73-4353-a98b-fd9f9f6629ba" name="Bulbiz Test"><con:settings/><con:runType>SEQUENTIAL</con:runType><con:testCase id="3ba67db9-4670-4de1-a1e8-f6464f8b780c" failOnError="true" failTestCaseOnErrors="true" keepSession="false" maxResults="0" name="Order" searchProperties="true"><con:settings/><con:testStep type="restrequest" name="POST - Account creation" id="55a65210-7105-433d-b8f6-eed9053846e6"><con:settings/><con:config service="bulbiz?_wadl" resourcePath="/cxf/bulbiz/client" methodName="POST" xsi:type="con:RestRequestStep" xmlns:xsi="http://www.w3.org/2001/XMLSchema-instance"><con:restRequest name="POST - Account creation" id="74804e59-3896-4567-8833-220c9f3193e2" mediaType="application/json" postQueryString="false"><con:settings><con:setting id="com.eviware.soapui.impl.wsdl.WsdlRequest@request-headers">&lt;xml-fragment/></con:setting></con:settings><con:endpoint>http://localhost:8181</con:endpoint><con:request/><con:originalUri>http://localhost/cxf/bulbiz/client</con:originalUri><con:assertion type="Valid HTTP Status Codes" id="64aa28e3-1895-49ad-8cc7-d2d1abe275be" name="Valid HTTP Status Codes"><con:configuration><codes>200</codes></con:configuration></con:assertion><con:credentials><con:authType>No Authorization</con:authType></con:credentials><con:jmsConfig JMSDeliveryMode="PERSISTENT"/><con:jmsPropertyConfig/><con:parameters><entry key="name" value="remy" xmlns="http://eviware.com/soapui/config"/></con:parameters></con:restRequest></con:config></con:testStep><con:testStep type="restrequest" name="PUT - Account modification" id="15c136ff-8e0b-40a3-9736-5e2d9335709d"><con:settings/><con:config service="bulbiz?_wadl" resourcePath="/cxf/bulbiz/client/{id}" methodName="PUT" xsi:type="con:RestRequestStep" xmlns:xsi="http://www.w3.org/2001/XMLSchema-instance"><con:restRequest name="PUT - Account modification" id="81b4f749-2230-4c2b-9015-91d8ee53a036" mediaType="application/json" postQueryString="false"><con:settings/><con:endpoint>http://localhost:8181</con:endpoint><con:request/><con:assertion type="Valid HTTP Status Codes" id="ec31dd2f-c887-4bbf-a922-562a65372d91" name="Valid HTTP Status Codes"><con:configuration><codes>200</codes></con:configuration></con:assertion><con:credentials><con:authType>No Authorization</con:authType></con:credentials><con:jmsConfig JMSDeliveryMode="PERSISTENT"/><con:jmsPropertyConfig/><con:parameters>
  <con:entry key="id" value="1"/>
  <con:entry key="name" value="jeremy"/>
</con:parameters></con:restRequest></con:config></con:testStep><con:testStep type="restrequest" name="PUT - Bad modification" id="36a804e2-87f4-4b5f-8922-aa0b8e361cbd"><con:settings/><con:config service="bulbiz?_wadl" resourcePath="/cxf/bulbiz/client/{id}" methodName="PUT" xsi:type="con:RestRequestStep" xmlns:xsi="http://www.w3.org/2001/XMLSchema-instance"><con:restRequest name="PUT - Bad modification" id="81b4f749-2230-4c2b-9015-91d8ee53a036" mediaType="application/json" postQueryString="false"><con:settings/><con:endpoint>http://localhost:8181</con:endpoint><con:request/><con:assertion type="Valid HTTP Status Codes" id="be2afe88-2f6d-4bdc-8d69-69bc1d61a52c" name="Valid HTTP Status Codes"><con:configuration><codes>404</codes></con:configuration></con:assertion><con:credentials><con:authType>No Authorization</con:authType></con:credentials><con:jmsConfig JMSDeliveryMode="PERSISTENT"/><con:jmsPropertyConfig/><con:parameters>
  <con:entry key="id" value="2"/>
  <con:entry key="name" value="sebastien"/>
</con:parameters></con:restRequest></con:config></con:testStep><con:testStep type="restrequest" name="GET - Check Account" id="997cb9bf-47c0-42de-9bad-0480295f5bc1"><con:settings/><con:config service="bulbiz?_wadl" resourcePath="/cxf/bulbiz/client/{id}" methodName="GET" xsi:type="con:RestRequestStep" xmlns:xsi="http://www.w3.org/2001/XMLSchema-instance"><con:restRequest name="GET - Check Account" id="f32e35bf-7dc5-45cc-aeae-2c4bedafc3af" mediaType="application/json"><con:settings/><con:endpoint>http://localhost:8181</con:endpoint><con:request/><con:assertion type="Valid HTTP Status Codes" id="39a25dca-d880-4ebb-a481-ac3b14823298" name="Valid HTTP Status Codes"><con:configuration><codes>200</codes></con:configuration></con:assertion><con:credentials><con:authType>No Authorization</con:authType></con:credentials><con:jmsConfig JMSDeliveryMode="PERSISTENT"/><con:jmsPropertyConfig/><con:parameters><entry key="id" value="1" xmlns="http://eviware.com/soapui/config"/></con:parameters></con:restRequest></con:config></con:testStep><con:testStep type="restrequest" name="POST - Add Item 1" id="2019f551-c803-46d9-a1d1-3d23f99964bd"><con:settings/><con:config service="bulbiz?_wadl" resourcePath="/cxf/bulbiz/cart/client/{id}/" methodName="POST" xsi:type="con:RestRequestStep" xmlns:xsi="http://www.w3.org/2001/XMLSchema-instance"><con:restRequest name="POST - Add Item 1" id="9a0b1c33-4c14-42ae-adbe-0a6df43c8cff" mediaType="application/json" postQueryString="false"><con:settings/><con:endpoint>http://localhost:8181</con:endpoint><con:request/><con:assertion type="Valid HTTP Status Codes" id="41bfc351-66d7-4442-a459-1d340b554d5e" name="Valid HTTP Status Codes"><con:configuration><codes>200</codes></con:configuration></con:assertion><con:credentials><con:authType>No Authorization</con:authType></con:credentials><con:jmsConfig JMSDeliveryMode="PERSISTENT"/><con:jmsPropertyConfig/><con:parameters>
  <con:entry key="id" value="1"/>
  <con:entry key="form" value="round"/>
  <con:entry key="color" value="blue"/>
  <con:entry key="quantity" value="12"/>
</con:parameters></con:restRequest></con:config></con:testStep><con:testStep type="restrequest" name="POST - Add Item 2" id="50a25783-9d2f-406b-ab7c-df16878e258e"><con:settings/><con:config service="bulbiz?_wadl" resourcePath="/cxf/bulbiz/cart/client/{id}/" methodName="POST" xsi:type="con:RestRequestStep" xmlns:xsi="http://www.w3.org/2001/XMLSchema-instance"><con:restRequest name="POST - Add Item 2" id="9a0b1c33-4c14-42ae-adbe-0a6df43c8cff" mediaType="application/json" postQueryString="false"><con:settings/><con:endpoint>http://localhost:8181</con:endpoint><con:request/><con:assertion type="Valid HTTP Status Codes" id="f1b59208-a435-4deb-ad4f-4a82ba543919" name="Valid HTTP Status Codes"><con:configuration><codes>200</codes></con:configuration></con:assertion><con:credentials><con:authType>No Authorization</con:authType></con:credentials><con:jmsConfig JMSDeliveryMode="PERSISTENT"/><con:jmsPropertyConfig/><con:parameters>
  <con:entry key="id" value="1"/>
  <con:entry key="form" value="Oval"/>
  <con:entry key="color" value="red"/>
  <con:entry key="quantity" value="5"/>
</con:parameters></con:restRequest></con:config></con:testStep><con:testStep type="restrequest" name="GET - Check Order" id="0cbf32fc-e18e-42e6-a2b1-d44e6354d1a5"><con:settings/><con:config service="bulbiz?_wadl" resourcePath="/cxf/bulbiz/cart/client/{id}/" methodName="GET" xsi:type="con:RestRequestStep" xmlns:xsi="http://www.w3.org/2001/XMLSchema-instance"><con:restRequest name="GET - Check Order" id="a5eb6633-bc8d-4690-a152-0e0a7e8e3b60" mediaType="application/json"><con:settings/><con:endpoint>http://localhost:8181</con:endpoint><con:request/><con:assertion type="Valid HTTP Status Codes" id="79942bf8-5c2a-45cd-a640-1289431bcb8a" name="Valid HTTP Status Codes"><con:configuration><codes>200</codes></con:configuration></con:assertion><con:credentials><con:authType>No Authorization</con:authType></con:credentials><con:jmsConfig JMSDeliveryMode="PERSISTENT"/><con:jmsPropertyConfig/><con:parameters><entry key="id" value="1" xmlns="http://eviware.com/soapui/config"/></con:parameters></con:restRequest></con:config></con:testStep><con:testStep type="restrequest" name="POST - Select destination" id="06714406-8a5c-4f49-804f-d79ff71e4ffb"><con:settings/><con:config service="bulbiz?_wadl" resourcePath="/cxf/bulbiz/delivery/destination/client/{clientId}" methodName="POST" xsi:type="con:RestRequestStep" xmlns:xsi="http://www.w3.org/2001/XMLSchema-instance"><con:restRequest name="POST - Select destination" id="43c54da4-fcbc-43bd-90ba-fb363cb8c75f" mediaType="application/json" postQueryString="false"><con:settings/><con:endpoint>http://localhost:8181</con:endpoint><con:request/><con:assertion type="Valid HTTP Status Codes" id="17db8b38-1b14-4f95-86e9-ba1e13717ddd" name="Valid HTTP Status Codes"><con:configuration><codes>200</codes></con:configuration></con:assertion><con:credentials><con:authType>No Authorization</con:authType></con:credentials><con:jmsConfig JMSDeliveryMode="PERSISTENT"/><con:jmsPropertyConfig/><con:parameters>
  <con:entry key="address" value="Sophia"/>
  <con:entry key="clientId" value="1"/>
</con:parameters></con:restRequest></con:config></con:testStep><con:testStep type="restrequest" name="POST - Paye" id="20729933-99a3-4330-b8f1-deb0fd2ecd43"><con:settings/><con:config service="bulbiz?_wadl" resourcePath="/cxf/bulbiz/transaction/pay/client/{userId}/order/{orderId}" methodName="POST" xsi:type="con:RestRequestStep" xmlns:xsi="http://www.w3.org/2001/XMLSchema-instance"><con:restRequest name="POST - Paye" id="c1086913-e438-4d31-bdb1-a3f3cbb71567" mediaType="application/json" postQueryString="false"><con:settings/><con:endpoint>http://localhost:8181</con:endpoint><con:request/><con:assertion type="Valid HTTP Status Codes" id="80ec3792-b2cd-47d7-ada8-3e10736144c7" name="Valid HTTP Status Codes"><con:configuration><codes>200</codes></con:configuration></con:assertion><con:credentials><con:authType>No Authorization</con:authType></con:credentials><con:jmsConfig JMSDeliveryMode="PERSISTENT"/><con:jmsPropertyConfig/><con:parameters>
  <con:entry key="userId" value="1"/>
  <con:entry key="sc" value="000"/>
  <con:entry key="date" value="06/34"/>
  <con:entry key="orderId" value="1"/>
  <con:entry key="numero" value="1234"/>
</con:parameters></con:restRequest></con:config></con:testStep><con:properties/></con:testCase><con:testCase id="6f8c56f5-e069-4f4a-8ca8-0b46a98a67e8" failOnError="true" failTestCaseOnErrors="true" keepSession="false" maxResults="0" name="Second Order" searchProperties="true"><con:settings/><con:testStep type="restrequest" name="POST - Add Item" id="5f9d20de-c486-485c-b22c-f5b75a10451e"><con:settings/><con:config service="bulbiz?_wadl" resourcePath="/cxf/bulbiz/cart/client/{id}/" methodName="POST" xsi:type="con:RestRequestStep" xmlns:xsi="http://www.w3.org/2001/XMLSchema-instance"><con:restRequest name="POST - Add Item" id="9a0b1c33-4c14-42ae-adbe-0a6df43c8cff" mediaType="application/json" postQueryString="false"><con:settings/><con:endpoint>http://localhost:8181</con:endpoint><con:request/><con:assertion type="Valid HTTP Status Codes" id="ecd0d267-4edd-4149-b6fc-1ff59bc7757b" name="Valid HTTP Status Codes"><con:configuration><codes>200</codes></con:configuration></con:assertion><con:credentials><con:authType>No Authorization</con:authType></con:credentials><con:jmsConfig JMSDeliveryMode="PERSISTENT"/><con:jmsPropertyConfig/><con:parameters>
  <con:entry key="id" value="1"/>
  <con:entry key="quantity" value="3"/>
</con:parameters></con:restRequest></con:config></con:testStep><con:testStep type="restrequest" name="DELETE - Delete Current Order" id="a2312403-2607-47bd-b4c4-70f756464ba2"><con:settings/><con:config service="bulbiz?_wadl" resourcePath="/cxf/bulbiz/cart/client/{id}/" methodName="DELETE" xsi:type="con:RestRequestStep" xmlns:xsi="http://www.w3.org/2001/XMLSchema-instance"><con:restRequest name="DELETE - Delete Current Order" id="d4b3b4b9-f4d8-45db-bf10-4fd838d1dca5" mediaType="application/json" postQueryString="false"><con:settings/><con:endpoint>http://localhost:8181</con:endpoint><con:request/><con:assertion type="Valid HTTP Status Codes" id="07ab9a55-3da7-4a0e-a688-b574ed26ec54" name="Valid HTTP Status Codes"><con:configuration><codes>200</codes></con:configuration></con:assertion><con:credentials><con:authType>No Authorization</con:authType></con:credentials><con:jmsConfig JMSDeliveryMode="PERSISTENT"/><con:jmsPropertyConfig/><con:parameters><entry key="id" value="1" xmlns="http://eviware.com/soapui/config"/></con:parameters></con:restRequest></con:config></con:testStep><con:testStep type="restrequest" name="POST - New Order" id="de812f67-b3b2-4ad0-9872-20a41331ca67"><con:settings/><con:config service="bulbiz?_wadl" resourcePath="/cxf/bulbiz/cart/client/{id}/" methodName="POST" xsi:type="con:RestRequestStep" xmlns:xsi="http://www.w3.org/2001/XMLSchema-instance"><con:restRequest name="POST - New Order" id="9a0b1c33-4c14-42ae-adbe-0a6df43c8cff" mediaType="application/json" postQueryString="false"><con:settings/><con:endpoint>http://localhost:8181</con:endpoint><con:request/><con:assertion type="Valid HTTP Status Codes" id="8f382c1e-99d1-4d7d-9897-7a37d8d2f7c1" name="Valid HTTP Status Codes"><con:configuration><codes>200</codes></con:configuration></con:assertion><con:credentials><con:authType>No Authorization</con:authType></con:credentials><con:jmsConfig JMSDeliveryMode="PERSISTENT"/><con:jmsPropertyConfig/><con:parameters>
  <con:entry key="id" value="1"/>
  <con:entry key="color" value="yellow"/>
  <con:entry key="quantity" value="6"/>
</con:parameters></con:restRequest></con:config></con:testStep><con:testStep type="restrequest" name="GET - Show current order" id="012535a1-db7f-44e2-8050-8f9276019275"><con:settings/><con:config service="bulbiz?_wadl" resourcePath="/cxf/bulbiz/cart/client/{id}/" methodName="GET" xsi:type="con:RestRequestStep" xmlns:xsi="http://www.w3.org/2001/XMLSchema-instance"><con:restRequest name="GET - Show current order" id="a5eb6633-bc8d-4690-a152-0e0a7e8e3b60" mediaType="application/json"><con:settings/><con:endpoint>http://localhost:8181</con:endpoint><con:request/><con:assertion type="Valid HTTP Status Codes" id="816563f1-7d6e-4b6b-a058-1b960d90b20e" name="Valid HTTP Status Codes"><con:configuration><codes>200</codes></con:configuration></con:assertion><con:credentials><con:authType>No Authorization</con:authType></con:credentials><con:jmsConfig JMSDeliveryMode="PERSISTENT"/><con:jmsPropertyConfig/><con:parameters><entry key="id" value="1" xmlns="http://eviware.com/soapui/config"/></con:parameters></con:restRequest></con:config></con:testStep><con:testStep type="restrequest" name="GET - View Specific Order" id="f019e36b-4805-4227-afc0-7efa41f420a7"><con:settings/><con:config service="bulbiz?_wadl" resourcePath="/cxf/bulbiz/cart/{orderId}/client/{clientId}/" methodName="GET" xsi:type="con:RestRequestStep" xmlns:xsi="http://www.w3.org/2001/XMLSchema-instance"><con:restRequest name="GET - View Specific Order" id="25cdf8d2-1661-4114-827e-b942d94234cd" mediaType="application/json"><con:settings/><con:endpoint>http://localhost:8181</con:endpoint><con:request/><con:assertion type="Valid HTTP Status Codes" id="4ae6b3cf-b050-40bb-a6df-da3a2adcbe5a" name="Valid HTTP Status Codes"><con:configuration><codes>200</codes></con:configuration></con:assertion><con:credentials><con:authType>No Authorization</con:authType></con:credentials><con:jmsConfig JMSDeliveryMode="PERSISTENT"/><con:jmsPropertyConfig/><con:parameters>
  <con:entry key="clientId" value="1"/>
  <con:entry key="orderId" value="1"/>
</con:parameters></con:restRequest></con:config></con:testStep><con:testStep type="restrequest" name="GET - Show history" id="2a403c84-d14f-4680-b994-bdfdebbc8af2"><con:settings/><con:config service="bulbiz?_wadl" resourcePath="/cxf/bulbiz/client/{clientId}/orders" methodName="GET" xsi:type="con:RestRequestStep" xmlns:xsi="http://www.w3.org/2001/XMLSchema-instance"><con:restRequest name="GET - Show history" id="d8884899-2368-4de3-a0b7-cfb4a49bae46" mediaType="application/json"><con:settings/><con:endpoint>http://localhost:8181</con:endpoint><con:request/><con:assertion type="Valid HTTP Status Codes" id="6c060b34-4b31-4c81-af66-a390482e167f" name="Valid HTTP Status Codes"><con:configuration><codes>200</codes></con:configuration></con:assertion><con:credentials><con:authType>No Authorization</con:authType></con:credentials><con:jmsConfig JMSDeliveryMode="PERSISTENT"/><con:jmsPropertyConfig/><con:parameters><entry key="clientId" value="1" xmlns="http://eviware.com/soapui/config"/></con:parameters></con:restRequest></con:config></con:testStep><con:testStep type="restrequest" name="POST - Select destination" id="c50ec84c-023d-4edf-a5b7-41c628ee437b"><con:settings/><con:config service="bulbiz?_wadl" resourcePath="/cxf/bulbiz/delivery/destination/client/{clientId}" methodName="POST" xsi:type="con:RestRequestStep" xmlns:xsi="http://www.w3.org/2001/XMLSchema-instance"><con:restRequest name="POST - Select destination" id="43c54da4-fcbc-43bd-90ba-fb363cb8c75f" mediaType="application/json" postQueryString="false"><con:settings/><con:endpoint>http://localhost:8181</con:endpoint><con:request/><con:assertion type="Valid HTTP Status Codes" id="feda75ed-5032-4676-a5a8-32c7bb6d3af9" name="Valid HTTP Status Codes"><con:configuration><codes>200</codes></con:configuration></con:assertion><con:credentials><con:authType>No Authorization</con:authType></con:credentials><con:jmsConfig JMSDeliveryMode="PERSISTENT"/><con:jmsPropertyConfig/><con:parameters>
  <con:entry key="address" value="Sophia"/>
  <con:entry key="clientId" value="1"/>
</con:parameters></con:restRequest></con:config></con:testStep><con:testStep type="restrequest" name="POST - Paye" id="4c632b00-61fc-4f6e-b44b-f0b4a63b0d94"><con:settings/><con:config service="bulbiz?_wadl" resourcePath="/cxf/bulbiz/transaction/pay/client/{userId}/order/{orderId}" methodName="POST" xsi:type="con:RestRequestStep" xmlns:xsi="http://www.w3.org/2001/XMLSchema-instance"><con:restRequest name="POST - Paye" id="c1086913-e438-4d31-bdb1-a3f3cbb71567" mediaType="application/json" postQueryString="false"><con:settings/><con:endpoint>http://localhost:8181</con:endpoint><con:request/><con:assertion type="Valid HTTP Status Codes" id="c03f1acb-5ff5-4225-8fa8-5042c7e3659b" name="Valid HTTP Status Codes"><con:configuration><codes>200</codes></con:configuration></con:assertion><con:credentials><con:authType>No Authorization</con:authType></con:credentials><con:jmsConfig JMSDeliveryMode="PERSISTENT"/><con:jmsPropertyConfig/><con:parameters>
  <con:entry key="userId" value="1"/>
  <con:entry key="sc" value="111"/>
  <con:entry key="date" value="23/45"/>
  <con:entry key="orderId" value="3"/>
  <con:entry key="numero" value="1234"/>
</con:parameters></con:restRequest></con:config></con:testStep><con:testStep type="restrequest" name="GET - View Manufacturing Test" id="ee3372b8-f613-4e48-8236-24f47573dd5a"><con:settings/><con:config service="bulbiz?_wadl" resourcePath="/cxf/bulbiz/delivery/manufacturing/order/{orderId}/client/{clientId}" methodName="GET" xsi:type="con:RestRequestStep" xmlns:xsi="http://www.w3.org/2001/XMLSchema-instance"><con:restRequest name="GET - View Manufacturing Test" id="dfb74fd9-3660-4678-99d4-049a0141dff7" mediaType="application/json"><con:settings/><con:endpoint>http://localhost:8181</con:endpoint><con:request/><con:assertion type="Valid HTTP Status Codes" id="294c285d-1f86-435e-98f1-b91368cf10c7" name="Valid HTTP Status Codes"><con:configuration><codes>200</codes></con:configuration></con:assertion><con:credentials><con:authType>No Authorization</con:authType></con:credentials><con:jmsConfig JMSDeliveryMode="PERSISTENT"/><con:jmsPropertyConfig/><con:parameters>
  <con:entry key="clientId" value="3"/>
  <con:entry key="orderId" value="1"/>
</con:parameters></con:restRequest></con:config></con:testStep><con:testStep type="restrequest" name="GET - View Delivery State" id="4b3e4249-8a15-4e99-9b5e-a09f6b04f43b"><con:settings/><con:config service="bulbiz?_wadl" resourcePath="/cxf/bulbiz/delivery/state/order/{orderId}/client/{clientId}" methodName="GET" xsi:type="con:RestRequestStep" xmlns:xsi="http://www.w3.org/2001/XMLSchema-instance"><con:restRequest name="GET - View Delivery State" id="f8a6d246-383e-4a97-8cc3-c663ef2dd0dd" mediaType="application/json"><con:settings/><con:endpoint>http://localhost:8181</con:endpoint><con:request/><con:assertion type="Valid HTTP Status Codes" id="2f17bb5a-783f-493f-abf5-5088f4699701" name="Valid HTTP Status Codes"><con:configuration><codes>200</codes></con:configuration></con:assertion><con:credentials><con:authType>No Authorization</con:authType></con:credentials><con:jmsConfig JMSDeliveryMode="PERSISTENT"/><con:jmsPropertyConfig/><con:parameters>
  <con:entry key="clientId" value="1"/>
  <con:entry key="orderId" value="3"/>
</con:parameters></con:restRequest></con:config></con:testStep><con:testStep type="restrequest" name="DELETE - Delete Account" id="94f9182a-4214-451b-a49d-3c0a0c551191"><con:settings/><con:config service="bulbiz?_wadl" resourcePath="/cxf/bulbiz/client/{id}" methodName="DELETE" xsi:type="con:RestRequestStep" xmlns:xsi="http://www.w3.org/2001/XMLSchema-instance"><con:restRequest name="DELETE - Delete Account" id="0d771f40-e100-4be8-b0d9-01c2392349ad" mediaType="application/json" postQueryString="false"><con:settings/><con:endpoint>http://localhost:8181</con:endpoint><con:request/><con:assertion type="Valid HTTP Status Codes" id="bdd30cc5-feaa-48cf-bafa-2cce17b2db8d" name="Valid HTTP Status Codes"><con:configuration><codes>200</codes></con:configuration></con:assertion><con:credentials><con:authType>No Authorization</con:authType></con:credentials><con:jmsConfig JMSDeliveryMode="PERSISTENT"/><con:jmsPropertyConfig/><con:parameters><entry key="id" value="1" xmlns="http://eviware.com/soapui/config"/></con:parameters></con:restRequest></con:config></con:testStep><con:properties/></con:testCase><con:testCase id="beb35c67-1c43-48cd-90a2-b760114ee78f" failOnError="true" failTestCaseOnErrors="true" keepSession="false" maxResults="0" name="Management" searchProperties="true"><con:settings/><con:testStep type="restrequest" name="POST - Add In Stock" id="5a691d62-6c69-4b23-b70a-83a6a5a964c8"><con:settings/><con:config service="bulbiz?_wadl" resourcePath="/cxf/bulbiz/stock" methodName="POST" xsi:type="con:RestRequestStep" xmlns:xsi="http://www.w3.org/2001/XMLSchema-instance"><con:restRequest name="POST - Add In Stock" id="f72b2842-3dbc-4fe4-b050-8f99de6635f1" mediaType="application/json" postQueryString="false"><con:settings/><con:endpoint>http://localhost:8181</con:endpoint><con:request/><con:assertion type="Valid HTTP Status Codes" id="fc846432-7358-4ec2-8be9-8fca7382c4f0" name="Valid HTTP Status Codes"><con:configuration><codes>200</codes></con:configuration></con:assertion><con:credentials><con:authType>No Authorization</con:authType></con:credentials><con:jmsConfig JMSDeliveryMode="PERSISTENT"/><con:jmsPropertyConfig/><con:parameters>
  <con:entry key="form" value="Round"/>
  <con:entry key="color" value="Blue"/>
  <con:entry key="quantity" value="2"/>
</con:parameters></con:restRequest></con:config></con:testStep><con:testStep type="restrequest" name="GET - Show Stock" id="0b7b9453-8aea-4acf-94d1-de60d938fc57"><con:settings/><con:config service="bulbiz?_wadl" resourcePath="/cxf/bulbiz/stock" methodName="GET" xsi:type="con:RestRequestStep" xmlns:xsi="http://www.w3.org/2001/XMLSchema-instance"><con:restRequest name="GET - Show Stock" id="855f7048-e038-4c5d-82ce-219b8b38ad2a" mediaType="application/json"><con:settings/><con:endpoint>http://localhost:8181</con:endpoint><con:request/><con:assertion type="Valid HTTP Status Codes" id="fabdc3d1-44fd-4c97-afaf-5ee4653bf9ab" name="Valid HTTP Status Codes"><con:configuration><codes>200</codes></con:configuration></con:assertion><con:credentials><con:authType>No Authorization</con:authType></con:credentials><con:jmsConfig JMSDeliveryMode="PERSISTENT"/><con:jmsPropertyConfig/><con:parameters/></con:restRequest></con:config></con:testStep><con:testStep type="restrequest" name="GET - Show Orders History" id="2da988e9-7ce2-4516-8e3f-6c1ec72d9e32"><con:settings/><con:config service="bulbiz?_wadl" resourcePath="/cxf/bulbiz/display/orders" methodName="GET" xsi:type="con:RestRequestStep" xmlns:xsi="http://www.w3.org/2001/XMLSchema-instance"><con:restRequest name="GET - Show Orders History" id="2f05c0fd-4e84-4505-bc4e-bd469146ff06" mediaType="application/json"><con:settings/><con:endpoint>http://localhost:8181</con:endpoint><con:request/><con:assertion type="Valid HTTP Status Codes" id="2dbe55bd-f578-45d9-8974-bd5b63cf51d9" name="Valid HTTP Status Codes"><con:configuration><codes>200</codes></con:configuration></con:assertion><con:credentials><con:authType>No Authorization</con:authType></con:credentials><con:jmsConfig JMSDeliveryMode="PERSISTENT"/><con:jmsPropertyConfig/><con:parameters/></con:restRequest></con:config></con:testStep><con:testStep type="restrequest" name="GET - Show Stock Quantity" id="087826ce-1f0f-46f4-9412-4b496d830cf9"><con:settings/><con:config service="bulbiz?_wadl" resourcePath="/cxf/bulbiz/display/bulbs" methodName="GET" xsi:type="con:RestRequestStep" xmlns:xsi="http://www.w3.org/2001/XMLSchema-instance"><con:restRequest name="GET - Show Stock Quantity" id="7953a20c-ed91-4b32-809b-d2f162802922" mediaType="application/json"><con:settings/><con:endpoint>http://localhost:8181</con:endpoint><con:request/><con:assertion type="Valid HTTP Status Codes" id="4b822640-926c-4d21-b700-f80b887b4fff" name="Valid HTTP Status Codes"><con:configuration><codes>200</codes></con:configuration></con:assertion><con:credentials><con:authType>No Authorization</con:authType></con:credentials><con:jmsConfig JMSDeliveryMode="PERSISTENT"/><con:jmsPropertyConfig/><con:parameters/></con:restRequest></con:config></con:testStep><con:testStep type="restrequest" name="GET - Sow number of member" id="52628663-5bcd-423c-a6d7-e0298281f53a"><con:settings/><con:config service="bulbiz?_wadl" resourcePath="/cxf/bulbiz/display/users" methodName="GET" xsi:type="con:RestRequestStep" xmlns:xsi="http://www.w3.org/2001/XMLSchema-instance"><con:restRequest name="GET - Sow number of member" id="7408cf1b-86cb-48ad-8588-f1a60a8bddd9" mediaType="application/json"><con:settings/><con:endpoint>http://localhost:8181</con:endpoint><con:request/><con:assertion type="Valid HTTP Status Codes" id="43e5075b-4918-4344-9fa8-14ce494e3136" name="Valid HTTP Status Codes"><con:configuration><codes>200</codes></con:configuration></con:assertion><con:credentials><con:authType>No Authorization</con:authType></con:credentials><con:jmsConfig JMSDeliveryMode="PERSISTENT"/><con:jmsPropertyConfig/><con:parameters/></con:restRequest></con:config></con:testStep><con:testStep type="restrequest" name="GET - Show specifiq order" id="8bd95d41-4ad3-4fd7-9649-da0805b1526e"><con:settings/><con:config service="bulbiz?_wadl" resourcePath="/cxf/bulbiz/display/order/{userId}/{orderId}" methodName="GET" xsi:type="con:RestRequestStep" xmlns:xsi="http://www.w3.org/2001/XMLSchema-instance"><con:restRequest name="GET - Show specifiq order" id="a91b498c-3373-4f30-89e3-bd17c5fda98b" mediaType="application/json"><con:settings/><con:endpoint>http://localhost:8181</con:endpoint><con:request/><con:assertion type="Valid HTTP Status Codes" id="da822638-3b66-41a3-a1e5-bb7cfab93a1a" name="Valid HTTP Status Codes"><con:configuration><codes>200</codes></con:configuration></con:assertion><con:credentials><con:authType>No Authorization</con:authType></con:credentials><con:jmsConfig JMSDeliveryMode="PERSISTENT"/><con:jmsPropertyConfig/><con:parameters><entry key="userId" value="1" xmlns="http://eviware.com/soapui/config"/></con:parameters></con:restRequest></con:config></con:testStep><con:properties/></con:testCase><con:properties/></con:testSuite><con:properties/><con:wssContainer/><con:oAuth2ProfileContainer/></con:soapui-project>